snpScore
