Metadata-Version: 2.1
Name: varBscore
Version: 1.0.3
Summary: A python package to calculate varBscore using vcf input
Home-page: https://github.com/bioShaun/omSnpScore
Author: lx Gui
Author-email: guilixuan@gmail.com
License: MIT
Keywords: bioinformatics,NGS,Reseq,SNP
Platform: UNKNOWN
